<svg xmlns="http://www.w3.org/2000/svg" version="1.1">
<defs>
    <marker id="arrow"
      viewBox="0 0 10 10" refX="0" refY="5"
      markerUnits="strokeWidth"
      markerWidth="4" markerHeight="3"
      orient="auto">
      <path d="M 0 0 L 10 5 L 0 10 z" />
    </marker>
  </defs>
<g stroke="#000000" fill="none" stroke-opacity="1.0" fill-opacity="1.0">
<rect x="0" y="0" width="500" height="1240" stroke-width="0" fill="none" />
<g stroke="#000000" fill="none" stroke-opacity="1.0" fill-opacity="1.0">
</g>
<g transform="rotate(85.0 250 620)" >
<g stroke="#000000" fill="none" stroke-opacity="1.0" fill-opacity="1.0">
</g>
<g stroke="#000000" fill="#34349C" stroke-opacity="1.0" fill-opacity="1.0">
<polygon points="27,612  27,582  477,582  477,612" stroke-width="1" />
<polygon points="27,692  477,692  477,722  27,722" stroke-width="1" />
</g>
<g stroke="#34349C" fill="none" stroke-opacity="1.0" fill-opacity="1.0">
<text x=" 171" y="659.0" font-family="Arial" font-size=" 25" fill="#34349C" stroke-width="0">Крылатское</text>
<text x=" 339" y="742.0" font-family="Arial" font-size=" 20" fill="#34349C" stroke-width="0">Молодёжная &gt;&gt;</text>
<text x=" 32" y="578.0" font-family="Arial" font-size=" 20" fill="#34349C" stroke-width="0">&lt;&lt; Строгино</text>
</g>
<g stroke="#000000" fill="none" stroke-opacity="1.0" fill-opacity="1.0">
<polyline points="27,692  27,678  16,678" stroke-width="1" fill="none"  />
<polyline points="-52,678  -62,678  -62,721  -154,721  -154,778  -28,778" stroke-width="1" fill="none"  />
<polyline points="-28,800  -218,800" stroke-width="1" fill="none"  />
<polyline points="-218,778  -176,778  -176,720  -187,720  -187,582  -183,582  -267,472  -318,472" stroke-width="1" fill="none"  />
<polyline points="-318,450  -178,450" stroke-width="1" fill="none"  />
<polyline points="-178,472  -238,472  -154,582  -63,582  -63,626  27,626  27,612" stroke-width="1" fill="none"  />
<line x1="-316" y1="472" x2="-316" y2="450" stroke-width="1" />
<line x1="-312" y1="472" x2="-312" y2="450" stroke-width="1" />
<line x1="-308" y1="472" x2="-308" y2="450" stroke-width="1" />
<line x1="-304" y1="472" x2="-304" y2="450" stroke-width="1" />
<line x1="-300" y1="472" x2="-300" y2="450" stroke-width="1" />
<line x1="-296" y1="472" x2="-296" y2="450" stroke-width="1" />
<line x1="-292" y1="472" x2="-292" y2="450" stroke-width="1" />
<line x1="-288" y1="472" x2="-288" y2="450" stroke-width="1" />
<line x1="-284" y1="472" x2="-284" y2="450" stroke-width="1" />
<line x1="-180" y1="472" x2="-180" y2="450" stroke-width="1" />
<line x1="-184" y1="472" x2="-184" y2="450" stroke-width="1" />
<line x1="-188" y1="472" x2="-188" y2="450" stroke-width="1" />
<line x1="-192" y1="472" x2="-192" y2="450" stroke-width="1" />
<line x1="-196" y1="472" x2="-196" y2="450" stroke-width="1" />
<line x1="-207" y1="472" x2="-207" y2="450" stroke-width="1" />
<line x1="-211" y1="472" x2="-211" y2="450" stroke-width="1" />
<line x1="-215" y1="472" x2="-215" y2="450" stroke-width="1" />
<line x1="-219" y1="472" x2="-219" y2="450" stroke-width="1" />
<line x1="-223" y1="472" x2="-223" y2="450" stroke-width="1" />
<line x1="-216" y1="800" x2="-216" y2="778" stroke-width="1" />
<line x1="-212" y1="800" x2="-212" y2="778" stroke-width="1" />
<line x1="-208" y1="800" x2="-208" y2="778" stroke-width="1" />
<line x1="-204" y1="800" x2="-204" y2="778" stroke-width="1" />
<line x1="-200" y1="800" x2="-200" y2="778" stroke-width="1" />
<line x1="-196" y1="800" x2="-196" y2="778" stroke-width="1" />
<line x1="-192" y1="800" x2="-192" y2="778" stroke-width="1" />
<line x1="-188" y1="800" x2="-188" y2="778" stroke-width="1" />
<line x1="-184" y1="800" x2="-184" y2="778" stroke-width="1" />
<line x1="-30" y1="800" x2="-30" y2="778" stroke-width="1" />
<line x1="-34" y1="800" x2="-34" y2="778" stroke-width="1" />
<line x1="-38" y1="800" x2="-38" y2="778" stroke-width="1" />
<line x1="-42" y1="800" x2="-42" y2="778" stroke-width="1" />
<line x1="-46" y1="800" x2="-46" y2="778" stroke-width="1" />
<line x1="-60" y1="800" x2="-60" y2="778" stroke-width="1" />
<line x1="-64" y1="800" x2="-64" y2="778" stroke-width="1" />
<line x1="-68" y1="800" x2="-68" y2="778" stroke-width="1" />
<line x1="-72" y1="800" x2="-72" y2="778" stroke-width="1" />
<line x1="-76" y1="800" x2="-76" y2="778" stroke-width="1" />
<line x1="8" y1="626" x2="8" y2="651" stroke-width="1" />
<line x1="4" y1="626" x2="4" y2="651" stroke-width="1" />
<line x1="0" y1="626" x2="0" y2="651" stroke-width="1" />
<line x1="-4" y1="626" x2="-4" y2="651" stroke-width="1" />
<line x1="-8" y1="626" x2="-8" y2="651" stroke-width="1" />
<line x1="-12" y1="626" x2="-12" y2="651" stroke-width="1" />
<line x1="-16" y1="626" x2="-16" y2="651" stroke-width="1" />
<line x1="-20" y1="626" x2="-20" y2="651" stroke-width="1" />
<line x1="-24" y1="626" x2="-24" y2="651" stroke-width="1" />
<line x1="-28" y1="626" x2="-28" y2="651" stroke-width="1" />
<line x1="-32" y1="626" x2="-32" y2="651" stroke-width="1" />
<line x1="-36" y1="626" x2="-36" y2="651" stroke-width="1" />
<line x1="-40" y1="626" x2="-40" y2="651" stroke-width="1" />
<line x1="-44" y1="626" x2="-44" y2="651" stroke-width="1" />
</g>
<g stroke="#000000" fill="#D0D0D0" stroke-opacity="1.0" fill-opacity="1.0">
<polygon points="-154,622  -144,622  -144,681  -154,681" stroke-width="1" />
</g>
<g stroke="#7F7F7F" fill="#D0D0D0" stroke-opacity="1.0" fill-opacity="1.0">
<line x1="10" y1="675" x2="10" y2="654" stroke-width="1" />
<line x1="6" y1="675" x2="6" y2="654" stroke-width="1" />
<line x1="2" y1="675" x2="2" y2="654" stroke-width="1" />
<line x1="-2" y1="675" x2="-2" y2="654" stroke-width="1" />
<line x1="-6" y1="675" x2="-6" y2="654" stroke-width="1" />
<line x1="-10" y1="675" x2="-10" y2="654" stroke-width="1" />
<line x1="-14" y1="675" x2="-14" y2="654" stroke-width="1" />
<line x1="-18" y1="675" x2="-18" y2="654" stroke-width="1" />
<line x1="-22" y1="675" x2="-22" y2="654" stroke-width="1" />
<line x1="-26" y1="675" x2="-26" y2="654" stroke-width="1" />
<line x1="-30" y1="675" x2="-30" y2="654" stroke-width="1" />
<line x1="-34" y1="675" x2="-34" y2="654" stroke-width="1" />
<line x1="-38" y1="675" x2="-38" y2="654" stroke-width="1" />
<line x1="-42" y1="675" x2="-42" y2="654" stroke-width="1" />
<line x1="-46" y1="675" x2="-46" y2="654" stroke-width="1" />
</g>
<g stroke="#000000" fill="#9B5509" stroke-opacity="1.0" fill-opacity="1.0">
<polygon points="16,654  -52,654  -52,651  16,651" stroke-width="1" />
<polygon points="16,662  16,667  -52,667  -52,662" stroke-width="1" />
<polygon points="16,675  -52,675  -52,678  16,678" stroke-width="1" />
</g>
<g stroke="#000000" fill="none" stroke-opacity="1.0" fill-opacity="1.0">
<polyline points="-63,609  -71,609  -71,582" stroke-width="1" fill="none"  />
<text x=" -74" y="618.0" font-family="Arial" font-size=" 10" fill="#000000" transform="rotate(-90.0  -74  608)" stroke-width="0">кассы</text>
</g>
<g stroke="#000000" fill="none" stroke-opacity="1.0" fill-opacity="1.0">
<polyline points="-73,610  -98,610" stroke-width=" 0.5" fill="none"  />
<polygon points="-101,668  -95,668  -95,674  -101,674" stroke-width="1" />
<polyline points="-101,671  -144,671" stroke-width=" 0.5" fill="none"  />
</g>
<g stroke="#009900" fill="none" stroke-opacity="1.0" fill-opacity="1.0">
<line x1="-100" y1="612" x2="-96" y2="612" stroke-width="1" />
<line x1="-100" y1="616" x2="-96" y2="616" stroke-width="1" />
<line x1="-100" y1="620" x2="-96" y2="620" stroke-width="1" />
<line x1="-100" y1="624" x2="-96" y2="624" stroke-width="1" />
<line x1="-100" y1="628" x2="-96" y2="628" stroke-width="1" />
<line x1="-100" y1="632" x2="-96" y2="632" stroke-width="1" />
<line x1="-100" y1="636" x2="-96" y2="636" stroke-width="1" />
<line x1="-100" y1="640" x2="-96" y2="640" stroke-width="1" />
<line x1="-100" y1="644" x2="-96" y2="644" stroke-width="1" />
<line x1="-100" y1="648" x2="-96" y2="648" stroke-width="1" />
<line x1="-100" y1="652" x2="-96" y2="652" stroke-width="1" />
<line x1="-100" y1="656" x2="-96" y2="656" stroke-width="1" />
<line x1="-100" y1="660" x2="-96" y2="660" stroke-width="1" />
<line x1="-100" y1="664" x2="-96" y2="664" stroke-width="1" />
</g>
<g stroke="#FF0000" fill="none" stroke-opacity="1.0" fill-opacity="1.0">
<line x1="-100" y1="678" x2="-96" y2="678" stroke-width="1" />
<line x1="-100" y1="682" x2="-96" y2="682" stroke-width="1" />
<line x1="-100" y1="686" x2="-96" y2="686" stroke-width="1" />
<line x1="-100" y1="690" x2="-96" y2="690" stroke-width="1" />
<line x1="-100" y1="694" x2="-96" y2="694" stroke-width="1" />
<line x1="-100" y1="698" x2="-96" y2="698" stroke-width="1" />
<line x1="-100" y1="702" x2="-96" y2="702" stroke-width="1" />
<line x1="-100" y1="706" x2="-96" y2="706" stroke-width="1" />
<line x1="-100" y1="710" x2="-96" y2="710" stroke-width="1" />
<line x1="-100" y1="714" x2="-96" y2="714" stroke-width="1" />
<line x1="-100" y1="718" x2="-96" y2="718" stroke-width="1" />
</g>
<g stroke="#FF0000" fill="none" stroke-opacity="1.0" fill-opacity="1.0">
<polyline points="-109,700  -126,700" marker-end="url(#arrow)" stroke-width="1" fill="none" />
<polyline points="40,663  24,663" marker-end="url(#arrow)" stroke-width="1" fill="none" />
</g>
<g stroke="#009900" fill="none" stroke-opacity="1.0" fill-opacity="1.0">
<polyline points="-126,634  -111,634" marker-end="url(#arrow)" stroke-width="1" fill="none" />
<polyline points="24,640  40,640" marker-end="url(#arrow)" stroke-width="1" fill="none" />
</g>
<g stroke="#000000" fill="none" stroke-opacity="1.0" fill-opacity="1.0">
<polyline points="477,612  477,626  566,626  566,582  665,582  665,469  573,469" stroke-width="1" fill="none"  />
<polyline points="573,447  687,447  687,551  747,551" stroke-width="1" fill="none"  />
<polyline points="747,574  687,574  687,582  691,582  691,721  687,721  687,778  746,778" stroke-width="1" fill="none"  />
<polyline points="746,800  578,800" stroke-width="1" fill="none"  />
<polyline points="578,778  665,778  665,721  565,721  565,678  555,678" stroke-width="1" fill="none"  />
<polyline points="487,678  477,678  477,692" stroke-width="1" fill="none"  />
<line x1="580" y1="800" x2="580" y2="778" stroke-width="1" />
<line x1="584" y1="800" x2="584" y2="778" stroke-width="1" />
<line x1="588" y1="800" x2="588" y2="778" stroke-width="1" />
<line x1="592" y1="800" x2="592" y2="778" stroke-width="1" />
<line x1="596" y1="800" x2="596" y2="778" stroke-width="1" />
<line x1="744" y1="800" x2="744" y2="778" stroke-width="1" />
<line x1="740" y1="800" x2="740" y2="778" stroke-width="1" />
<line x1="736" y1="800" x2="736" y2="778" stroke-width="1" />
<line x1="732" y1="800" x2="732" y2="778" stroke-width="1" />
<line x1="728" y1="800" x2="728" y2="778" stroke-width="1" />
<line x1="724" y1="800" x2="724" y2="778" stroke-width="1" />
<line x1="720" y1="800" x2="720" y2="778" stroke-width="1" />
<line x1="716" y1="800" x2="716" y2="778" stroke-width="1" />
<line x1="712" y1="800" x2="712" y2="778" stroke-width="1" />
<line x1="610" y1="800" x2="610" y2="778" stroke-width="1" />
<line x1="614" y1="800" x2="614" y2="778" stroke-width="1" />
<line x1="618" y1="800" x2="618" y2="778" stroke-width="1" />
<line x1="622" y1="800" x2="622" y2="778" stroke-width="1" />
<line x1="626" y1="800" x2="626" y2="778" stroke-width="1" />
<line x1="745" y1="574" x2="745" y2="551" stroke-width="1" />
<line x1="741" y1="574" x2="741" y2="551" stroke-width="1" />
<line x1="737" y1="574" x2="737" y2="551" stroke-width="1" />
<line x1="733" y1="574" x2="733" y2="551" stroke-width="1" />
<line x1="729" y1="574" x2="729" y2="551" stroke-width="1" />
<line x1="725" y1="574" x2="725" y2="551" stroke-width="1" />
<line x1="721" y1="574" x2="721" y2="551" stroke-width="1" />
<line x1="717" y1="574" x2="717" y2="551" stroke-width="1" />
<line x1="713" y1="574" x2="713" y2="551" stroke-width="1" />
<line x1="575" y1="469" x2="575" y2="447" stroke-width="1" />
<line x1="579" y1="469" x2="579" y2="447" stroke-width="1" />
<line x1="583" y1="469" x2="583" y2="447" stroke-width="1" />
<line x1="587" y1="469" x2="587" y2="447" stroke-width="1" />
<line x1="591" y1="469" x2="591" y2="447" stroke-width="1" />
<line x1="606" y1="469" x2="606" y2="447" stroke-width="1" />
<line x1="610" y1="469" x2="610" y2="447" stroke-width="1" />
<line x1="614" y1="469" x2="614" y2="447" stroke-width="1" />
<line x1="618" y1="469" x2="618" y2="447" stroke-width="1" />
<line x1="622" y1="469" x2="622" y2="447" stroke-width="1" />
<line x1="494" y1="626" x2="494" y2="651" stroke-width="1" />
<line x1="498" y1="626" x2="498" y2="651" stroke-width="1" />
<line x1="502" y1="626" x2="502" y2="651" stroke-width="1" />
<line x1="506" y1="626" x2="506" y2="651" stroke-width="1" />
<line x1="510" y1="626" x2="510" y2="651" stroke-width="1" />
<line x1="514" y1="626" x2="514" y2="651" stroke-width="1" />
<line x1="518" y1="626" x2="518" y2="651" stroke-width="1" />
<line x1="522" y1="626" x2="522" y2="651" stroke-width="1" />
<line x1="526" y1="626" x2="526" y2="651" stroke-width="1" />
<line x1="530" y1="626" x2="530" y2="651" stroke-width="1" />
<line x1="534" y1="626" x2="534" y2="651" stroke-width="1" />
<line x1="538" y1="626" x2="538" y2="651" stroke-width="1" />
<line x1="542" y1="626" x2="542" y2="651" stroke-width="1" />
<line x1="546" y1="626" x2="546" y2="651" stroke-width="1" />
</g>
<g stroke="#000000" fill="#D0D0D0" stroke-opacity="1.0" fill-opacity="1.0">
<polygon points="656,622  665,622  665,681  656,681" stroke-width="1" />
</g>
<g stroke="#7F7F7F" fill="#D0D0D0" stroke-opacity="1.0" fill-opacity="1.0">
<line x1="548" y1="675" x2="548" y2="654" stroke-width="1" />
<line x1="544" y1="675" x2="544" y2="654" stroke-width="1" />
<line x1="540" y1="675" x2="540" y2="654" stroke-width="1" />
<line x1="536" y1="675" x2="536" y2="654" stroke-width="1" />
<line x1="532" y1="675" x2="532" y2="654" stroke-width="1" />
<line x1="528" y1="675" x2="528" y2="654" stroke-width="1" />
<line x1="524" y1="675" x2="524" y2="654" stroke-width="1" />
<line x1="520" y1="675" x2="520" y2="654" stroke-width="1" />
<line x1="516" y1="675" x2="516" y2="654" stroke-width="1" />
<line x1="512" y1="675" x2="512" y2="654" stroke-width="1" />
<line x1="508" y1="675" x2="508" y2="654" stroke-width="1" />
<line x1="504" y1="675" x2="504" y2="654" stroke-width="1" />
<line x1="500" y1="675" x2="500" y2="654" stroke-width="1" />
<line x1="496" y1="675" x2="496" y2="654" stroke-width="1" />
<line x1="492" y1="675" x2="492" y2="654" stroke-width="1" />
</g>
<g stroke="#000000" fill="#9B5509" stroke-opacity="1.0" fill-opacity="1.0">
<polygon points="555,654  487,654  487,651  555,651" stroke-width="1" />
<polygon points="555,662  555,667  487,667  487,662" stroke-width="1" />
<polygon points="555,675  487,675  487,678  555,678" stroke-width="1" />
</g>
<g stroke="#000000" fill="none" stroke-opacity="1.0" fill-opacity="1.0">
<polyline points="566,609  574,609  574,582" stroke-width="1" fill="none"  />
<text x=" 563" y="618.0" font-family="Arial" font-size=" 10" fill="#000000" transform="rotate(-90.0  563  608)" stroke-width="0">кассы</text>
</g>
<g stroke="#000000" fill="none" stroke-opacity="1.0" fill-opacity="1.0">
<polyline points="576,610  601,610" stroke-width=" 0.5" fill="none"  />
<polygon points="604,668  598,668  598,674  604,674" stroke-width="1" />
<polyline points="604,671  656,671" stroke-width=" 0.5" fill="none"  />
</g>
<g stroke="#009900" fill="none" stroke-opacity="1.0" fill-opacity="1.0">
<line x1="603" y1="612" x2="599" y2="612" stroke-width="1" />
<line x1="603" y1="616" x2="599" y2="616" stroke-width="1" />
<line x1="603" y1="620" x2="599" y2="620" stroke-width="1" />
<line x1="603" y1="624" x2="599" y2="624" stroke-width="1" />
<line x1="603" y1="628" x2="599" y2="628" stroke-width="1" />
<line x1="603" y1="632" x2="599" y2="632" stroke-width="1" />
<line x1="603" y1="636" x2="599" y2="636" stroke-width="1" />
<line x1="603" y1="640" x2="599" y2="640" stroke-width="1" />
<line x1="603" y1="644" x2="599" y2="644" stroke-width="1" />
<line x1="603" y1="648" x2="599" y2="648" stroke-width="1" />
<line x1="603" y1="652" x2="599" y2="652" stroke-width="1" />
<line x1="603" y1="656" x2="599" y2="656" stroke-width="1" />
<line x1="603" y1="660" x2="599" y2="660" stroke-width="1" />
<line x1="603" y1="664" x2="599" y2="664" stroke-width="1" />
</g>
<g stroke="#FF0000" fill="none" stroke-opacity="1.0" fill-opacity="1.0">
<line x1="603" y1="678" x2="599" y2="678" stroke-width="1" />
<line x1="603" y1="682" x2="599" y2="682" stroke-width="1" />
<line x1="603" y1="686" x2="599" y2="686" stroke-width="1" />
<line x1="603" y1="690" x2="599" y2="690" stroke-width="1" />
<line x1="603" y1="694" x2="599" y2="694" stroke-width="1" />
<line x1="603" y1="698" x2="599" y2="698" stroke-width="1" />
<line x1="603" y1="702" x2="599" y2="702" stroke-width="1" />
<line x1="603" y1="706" x2="599" y2="706" stroke-width="1" />
<line x1="603" y1="710" x2="599" y2="710" stroke-width="1" />
<line x1="603" y1="714" x2="599" y2="714" stroke-width="1" />
<line x1="603" y1="718" x2="599" y2="718" stroke-width="1" />
</g>
<g stroke="#FF0000" fill="none" stroke-opacity="1.0" fill-opacity="1.0">
<polyline points="621,700  636,700" marker-end="url(#arrow)" stroke-width="1" fill="none" />
<polyline points="463,663  479,663" marker-end="url(#arrow)" stroke-width="1" fill="none" />
</g>
<g stroke="#009900" fill="none" stroke-opacity="1.0" fill-opacity="1.0">
<polyline points="636,633  621,633" marker-end="url(#arrow)" stroke-width="1" fill="none" />
<polyline points="479,640  463,640" marker-end="url(#arrow)" stroke-width="1" fill="none" />
</g>
<g stroke="#00AFAF" fill="none" stroke-opacity="1.0" fill-opacity="1.0">
<text x=" -355" y="658.0" font-family="Arial" font-size=" 15" fill="#00AFAF" stroke-width="0">Осенний бульвар</text>
<text x=" 747" y="656.0" font-family="Arial" font-size=" 15" fill="#00AFAF" stroke-width="0">Осенний бульвар</text>
</g>
</g>
</g>
</svg>
